Py3DR/__init__.py
Py3DR-0.1.0.dist-info/METADATA
Py3DR-0.1.0.dist-info/WHEEL
Py3DR-0.1.0.dist-info/top_level.txt
Py3DR-0.1.0.dist-info/RECORD
