Metadata-Version: 2.1
Name: Py3DR
Version: 0.1.0
Summary: A simple package for 3D Reconstruction
Home-page: https://github.com/HerbHSSO/Py3DR
Author: HerbHSSO
License: UNKNOWN
Platform: UNKNOWN
Requires-Python: >=3.6
Requires-Dist: opencv-contrib-python
Requires-Dist: open3d
Requires-Dist: numpy
